ndoptimize/__init__.py
ndoptimize-0.0.0.dist-info/METADATA
ndoptimize-0.0.0.dist-info/WHEEL
ndoptimize-0.0.0.dist-info/top_level.txt
ndoptimize-0.0.0.dist-info/RECORD
